redcross/__init__.py
redcross/align.py
redcross/cross_correlation.py
redcross/datacube.py
redcross/pipeline.py
redcross/planet.py
redcross/read.py
redcross/sysrem.py
redcross-0.0.2.dist-info/LICENSE
redcross-0.0.2.dist-info/METADATA
redcross-0.0.2.dist-info/WHEEL
redcross-0.0.2.dist-info/top_level.txt
redcross-0.0.2.dist-info/RECORD
