Metadata-Version: 2.1
Name: redcross
Version: 0.0.2
Summary: Reduction and cross-correlation of high-resolution spectroscopy for exoplanet atmospheres
Home-page: https://github.com/DGonzalezPicos/redcross
Author: Darío González Picos
Author-email: Darío González Picos <dariogonzalezpicos@gmail.com>
License: BSD 3-Clause License        
Project-URL: Homepage, https://github.com/DGonzalezPicos/redcross
Project-URL: Bug Tracker, https://github.com/DGonzalezPicos/redcross/issues
Classifier: Programming Language :: Python :: 3
Classifier: License :: OSI Approved :: MIT License
Classifier: Operating System :: OS Independent
Requires-Python: >=3.7
License-File: LICENSE
Requires-Dist: importlib-metadata (>=2.0) ; python_version < "3.8"
Provides-Extra: docs
Requires-Dist: sphinx ; extra == 'docs'
Requires-Dist: sphinx-automodapi ; extra == 'docs'
Requires-Dist: numpydoc ; extra == 'docs'
Provides-Extra: test
Requires-Dist: pytest ; extra == 'test'
Requires-Dist: pytest-doctestplus ; extra == 'test'
Requires-Dist: flake8 ; extra == 'test'
Requires-Dist: codecov ; extra == 'test'
Requires-Dist: pytest-cov ; extra == 'test'
